orchestrator_logger/__init__.py
orchestrator_logger/logger.py
orchestrator_logger-1.0.1.dist-info/licenses/LICENSE
orchestrator_logger-1.0.1.dist-info/METADATA
orchestrator_logger-1.0.1.dist-info/WHEEL
orchestrator_logger-1.0.1.dist-info/top_level.txt
orchestrator_logger-1.0.1.dist-info/RECORD
