Metadata-Version: 2.4
Name: orchestrator-logger
Version: 1.0.1
Summary: A simple logger for orchestrator API
Author-email: Orchestrator Robot Logger <tech-support@kineticstaff.com>
License: MIT
Requires-Python: >=3.7
License-File: LICENSE
Requires-Dist: requests
Dynamic: license-file
